MANIFEST.in
README.rst
setup.cfg
setup.py
renogy_rover/__init__.py
renogy_rover/__main__.py
renogy_rover/driver.py
renogy_rover/schema.py
renogy_rover/settings.yaml
renogy_rover.egg-info/PKG-INFO
renogy_rover.egg-info/SOURCES.txt
renogy_rover.egg-info/dependency_links.txt
renogy_rover.egg-info/entry_points.txt
renogy_rover.egg-info/requires.txt
renogy_rover.egg-info/top_level.txt